stalebot/__init__.py
stalebot/__main__.py
stalebot/hooks.py
stalebot-0.2.0.dist-info/licenses/LICENSE
stalebot-0.2.0.dist-info/METADATA
stalebot-0.2.0.dist-info/WHEEL
stalebot-0.2.0.dist-info/entry_points.txt
stalebot-0.2.0.dist-info/top_level.txt
stalebot-0.2.0.dist-info/RECORD
